cybersift/__init__.py
cybersift/siem.py
cybersift/tutela.py
tests/__init__.py
tests/test_sdk.py
cybersift_sdk-0.1.3.4.dist-info/LICENSE
cybersift_sdk-0.1.3.4.dist-info/METADATA
cybersift_sdk-0.1.3.4.dist-info/WHEEL
cybersift_sdk-0.1.3.4.dist-info/top_level.txt
cybersift_sdk-0.1.3.4.dist-info/RECORD
