Metadata-Version: 2.1
Name: cybersift_sdk
Version: 0.1.3.4
Summary: A python helper for the various CyberSift APIs
Author: CyberSift
Author-email: david.vassallo@cybersfit.io
Classifier: Programming Language :: Python :: 3
Classifier: Operating System :: OS Independent
Requires-Python: >=3.6
License-File: LICENSE
Requires-Dist: requests
Requires-Dist: python-dotenv
Requires-Dist: build
